eskiz/__init__.py
eskiz/client/__init__.py
eskiz/client/async_client.py
eskiz/client/http.py
eskiz/client/sync.py
eskiz/enum/__init__.py
eskiz/enum/network.py
eskiz/exception/__init__.py
eskiz/exception/token.py
eskiz/request/__init__.py
eskiz/request/batch.py
eskiz/request/login.py
eskiz/request/messages.py
eskiz/request/reports.py
eskiz/request/send.py
eskiz/response/__init__.py
eskiz/response/batch.py
eskiz/response/limit.py
eskiz/response/login.py
eskiz/response/messages.py
eskiz/response/refresh.py
eskiz/response/reports.py
eskiz/response/send.py
eskiz/response/templates.py
eskiz/response/user.py
eskiz_pkg-2.0.1.dist-info/licenses/LICENSE.md
eskiz_pkg-2.0.1.dist-info/METADATA
eskiz_pkg-2.0.1.dist-info/WHEEL
eskiz_pkg-2.0.1.dist-info/top_level.txt
eskiz_pkg-2.0.1.dist-info/RECORD
