Metadata-Version: 2.4
Name: eskiz-pkg
Version: 2.0.1
Summary: Python client for Eskiz.uz SMS API
Author-email: Muhammadali Akbarov <muhammadali17abc@gmail.com>
License-Expression: MIT
Project-URL: Homepage, https://github.com/Muhammadali-Akbarov/eskiz-pkg
Project-URL: Issues, https://github.com/Muhammadali-Akbarov/eskiz-pkg/issues
Keywords: eskiz,sms,smspy,eskizuz,eskiz-pkg,sms-service,smsuz
Classifier: Development Status :: 5 - Production/Stable
Classifier: Intended Audience :: Developers
Classifier: Programming Language :: Python :: 3
Classifier: Programming Language :: Python :: 3.7
Classifier: Programming Language :: Python :: 3.8
Classifier: Programming Language :: Python :: 3.9
Classifier: Programming Language :: Python :: 3.10
Classifier: Programming Language :: Python :: 3.11
Classifier: Programming Language :: Python :: 3.12
License-File: LICENSE.md
Requires-Dist: requests
Requires-Dist: pydantic
Provides-Extra: async
Requires-Dist: aiohttp>=3.8.0; extra == "async"
Provides-Extra: dev
Requires-Dist: pytest; extra == "dev"
Requires-Dist: pytest-asyncio; extra == "dev"
Requires-Dist: flake8; extra == "dev"
Requires-Dist: mypy; extra == "dev"
Dynamic: license-file
